Workbook

Sheet BTC
B1: Balance | C1: BTH for BTC | D1: BTC | E1: BTH for ETH | F1: ETH | G1: BTH for BCH | H1: BCH | K1: Actul X-rate | L1: Total investment | M1: Spot rate
A2: 42907 | B2: =99500-C2 -> 49500 | C2: 50000 | D2: 0.51769316 | K2: =C2/D2 -> 96582.308 | L2: =C2+B29+E2 -> 55587.651 | M2: 96100
A3: 42911 | B3: 98712.96 | D3: 2.34e-06 | L3: =C3+B3+E3 -> 98712.96
A4: 42914 | B4: 832.97 | D4: 4.7817681 | K4: =E4/D4 -> 0 | L4: =C4+B4+E4 -> 832.97 | M4: 9988 | N4: 7150.01
A5: 43147 | B5: =G5*H5+C5*D5+E5*F5 -> 67638.803 | C5: 318690 | D5: 2.34e-06 | E5: 29520 | F5: 2.2912584 | G5: 47005 | H5: 2.34e-06
A6: 43155 | B6: =G6*H6+C6*D6+E6*F6 -> 63672.645 | C6: 323000 | D6: 2.34e-06 | E6: 27789 | F6: 2.2912584 | G6: 47005 | H6: 2.34e-06
A7: 43421 | B7: =G7*H7+C7*D7+E7*F7 -> 6236.99 | C7: 181000.01 | D7: 2.34e-06 | E7: 5715 | F7: 1.0912584 | G7: 10592 | H7: 2.34e-06
A8: 43436 | B8: =G8*H8+C8*D8+E8*F8 -> 4138.3817 | C8: 135380 | D8: 2.34e-06 | E8: 3792 | F8: 1.0912584 | G8: 5601 | H8: 2.34e-06
A9: 43443 | B9: =G9*H9+C9*D9+E9*F9 -> 3248.946 | C9: 112002 | D9: 2.34e-06 | E9: 2977 | F9: 1.0912584 | G9: 3300 | H9: 2.34e-06
A10: 43449 | B10: =G10*H10+C10*D10+E10*F10 -> 3021.5442 | C10: 105754.27 | D10: 2.34e-06 | E10: 2768.63 | F10: 1.0912584 | G10: 2577 | H10: 2.34e-06
A11: 43456 | B11: =G11*H11+C11*D11+E11*F11 -> 3797.907 | C11: 124540 | D11: 2.34e-06 | E11: 3480.02 | F11: 1.0912584 | G11: 6250 | H11: 2.34e-06
A12: 43462 | B12: =G12*H12+C12*D12+E12*F12 -> 4136.1587 | C12: 118750 | D12: 2.34e-06 | E12: 3790 | F12: 1.0912584 | G12: 4950 | H12: 2.34e-06
A13: 43470 | B13: =G13*H13+C13*D13+E13*F13 -> 5444.5842 | C13: 121500 | D13: 2.34e-06 | E13: 4989 | F13: 1.0912584 | G13: 5070 | H13: 2.34e-06
A14: 43476 | B14: =G14*H14+C14*D14+E14*F14 -> 4473.3565 | C14: 119000 | D14: 2.34e-06 | E14: 4099 | F14: 1.0912584 | G14: 4244.28 | H14: 2.34e-06
A15: 43485 | B15: =G15*H15+C15*D15+E15*F15 -> 4272.5611 | C15: 117500 | D15: 2.34e-06 | E15: 3915 | F15: 1.0912584 | G15: 4100 | H15: 2.34e-06
A16: 43491 | B16: =G16*H16+C16*D16+E16*F16 -> 3962.0869 | C16: 112813 | D16: 2.34e-06 | E16: 3630.5 | F16: 1.0912584 | G16: 3988 | H16: 2.34e-06
... A47: 43715 | B47: =G47*H47+C47*D47+E47*F47 -> 5569.4481 | C47: 314700 | D47: 2.34e-06 | E47: 5103 | F47: 1.0912584 | G47: 8610 | H47: 2.34e-06
A48: 44276

Sheet Zipmex
B1: THB | C1: ZMT Spot rate | D1: ZMT (Buy) | E1: ZMT Value (THB) | F1: ZMT (Yield) | G1: % Yield ZMT | H1: ZMT (Net) | I1: ZMT (THB) | J1: USDT Spot rate | K1: USDT (Buy) | L1: USDT Value (THB) | M1: USDT (Yield) | N1: % Yield USDT | O1: USDT (Net) | P1: USDT (THB) | Q1: Net Yield (THB) | R1: %Net Yield (%) | S1: =S2-B2 -> -324772 | V1: BTC Cost | W1: LTC Cost | X1: USDC Cost | Y1: ZMT Cost
A2: Date\Total | B2: =SUM(B3:B1000) -> 638000 | C2: =AVERAGE(C3:C1000) -> 79.841951 | D2: =SUM(D3:D1000) -> 2372.8549 | E2: =C2*D2 -> 189453.37 | F2: =SUM(F3:F1000) -> 5.3308654 | G2: =(H2-D2)/D2 -> 0.002246604 | H2: =(D2+F2) -> 2378.1858 | I2: =H2*69.28 -> 164760.71 | J2: =AVERAGE(J3:J1000) -> 31.696875 | K2: =SUM(K3:K1000) -> 122.1888 | L2: =J2*K2 -> 3873.0031 | M2: =SUM(M3:M1000) -> 4.7252032 | N2: =(O2-K2)/K2 -> 0.038671329 | O2: =(K2+M2) -> 126.914 | P2: =O2*31.5001 -> 3997.8038 | Q2: =(P2+I2)-B2 -> -469241.49 | R2: =Q2/B2 -> -0.73548822 | S2: 313228 | T2: =(S2-B2)/B2 -> -0.50904702 | V2: 1661713 | W2: 6439 | X2: 32.5 | Y2: 68.2
A3: 44277 | B3: 6000 | C3: 65 | D3: 46.1538 | E3: =C3*D3 -> 2999.997 | F3: 0.01877134 | J3: 31.15 | K3: 96.2806 | L3: =J3*K3 -> 2999.1407 | M3: 0.02152178 | V3: 21823.2 | W3: =7614-5296 -> 2318 | X3: =116398-6065 -> 110333 | Y3: =405998-65201 -> 340797
A4: 44278 | B4: 3780 | F4: =0.00000583+0.01877134 -> 0.01877717 | M4: 0.02152659
A5: 44279 | C5: 69.47 | D5: 54.4042 | E5: =C5*D5 -> 3779.4598 | F5: =0.00001166+0.01877134 -> 0.018783 | M5: 0.0215314 | V5: =25000-V3 -> 3176.8
A6: 44280 | B6: =220+7000 -> 7220 | C6: 75.15 | D6: 101.1946 | E6: =C6*D6 -> 7604.7742 | F6: =0.00000583+0.0409135 -> 0.04091933 | J6: 32.13 | K6: =-50+0.0015+50.0062+6.8724 -> 6.8801 | L6: =J6*K6 -> 221.05761 | M6: 0.02153621
A7: 44281 | C7: 69.5 | D7: 22.8177 | E7: =C7*D7 -> 1585.8302 | F7: 0.08209492 | J7: 31.71 | K7: =-0.9691-23.4884-25.5425 -> -50 | L7: =J7*K7 -> -1585.5 | M7: 0.02307895
A8: 44282 | B8: 4000 | C8: 69.35 | D8: 21.6278 | E8: =C8*D8 -> 1499.8879 | F8: =0.08209492+0.00711125 -> 0.08920617 | M8: 0.01190752
A9: 44283 | B9: 80000 | C9: 69.5 | D9: 43.1531 | E9: =C9*D9 -> 2999.1405 | F9: =0.09999029+0.00019154 -> 0.10018183 | G9: =B9*1%*5/12 -> 333.33333 | J9: 31.45 | K9: 47.6809 | L9: =J9*K9 -> 1499.5643 | M9: 0.01191018
C10: 69.5 | D10: 43.1597 | E10: =C10*D10 -> 2999.5992 | J10: 31.4 | K10: 31.8471 | L10: =J10*K10 -> 999.99894
C11: 69.5 | D11: 43.1654 | E11: =C11*D11 -> 2999.9953 | J11: 31.36 | K11: 31.8877 | L11: =J11*K11 -> 999.99827
C12: 69.4 | D12: 57.6323 | E12: =C12*D12 -> 3999.6816 | J12: 31.35 | K12: 63.7958 | L12: =J12*K12 -> 1999.9983
C13: 69.25 | D13: 38.9285 | E13: =C13*D13 -> 2695.7986 | J13: 31.32 | K13: 0.0048 | L13: =J13*K13 -> 0.150336
C14: 69.28 | D14: 18.8298 | E14: =C14*D14 -> 1304.5285 | J14: 31.32 | K14: 95.7653 | L14: =J14*K14 -> 2999.3692
C15: 69.15 | D15: 15.5666 | E15: =C15*D15 -> 1076.4304 | J15: 31.34 | K15: 63.8162 | L15: =J15*K15 -> 1999.9997
C16: 69.21 | D16: 43.3463 | E16: =C16*D16 -> 2999.9974
C17: 69.2 | D17: 1.3154 | E17: =C17*D17 -> 91.02568
C18: 69.21 | D18: 28.8975 | E18: =C18*D18 -> 1999.996
C19: 69.2 | D19: 0.1294 | E19: =C19*D19 -> 8.95448
C20: 69.2 | D20: 43.3526 | E20: =C20*D20 -> 2999.9999
C21: 69.35 | D21: 1.4626 | E21: =C21*D21 -> 101.43131
C22: 69.35 | D22: 1 | E22: =C22*D22 -> 69.35
C23: 69.35 | D23: 40.7961 | E23: =C23*D23 -> 2829.2095
C24: 69.35 | D24: 43.2587 | E24: =C24*D24 -> 2999.9908
C25: 69.19 | D25: 43.3588 | E25: =C25*D25 -> 2999.9954
C26: 69.3 | D26: 28.86 | E26: =C26*D26 -> 1999.998
C27: 69.3 | D27: 14.4299 | E27: =C27*D27 -> 999.99207
A28: 44284 | C28: 69.27 | D28: 28.8724 | E28: =C28*D28 -> 1999.9911 | F28: =0.03125342+0.40705848 -> 0.4383119 | J28: 31.28 | K28: 127.8367 | L28: =J28*K28 -> 3998.732 | M28: 0.08675079
C29: 69.15 | D29: 43.3783 | E29: =C29*D29 -> 2999.6094
C30: 68.89 | D30: 72.5689 | E30: =C30*D30 -> 4999.2715
C31: 68.8 | D31: 0.1 | E31: =C31*D31 -> 6.88
C32: 68.89 | D32: 8.2821 | E32: =C32*D32 -> 570.55387
C33: 68.89 | D33: 35.2174 | E33: =C33*D33 -> 2426.1267
C34: 68.77 | D34: 72.6987 | E34: =C34*D34 -> 4999.4896
C35: 69.5 | D35: -50.3214 | E35: =C35*D35 -> -3497.3373
C36: 68.5 | D36: 40.9102 | E36: =C36*D36 -> 2802.3487
C37: 68.5 | D37: 2.8854 | E37: =C37*D37 -> 197.6499
A38: 44285 | C38: 69.5 | D38: -50.3214 | E38: =C38*D38 -> -3497.3373 | F38: =0.02936302+0.40705848 -> 0.4364215 | M38: 0.11534575
C39: 69.99 | D39: -25.7142 | E39: =C39*D39 -> -1799.7369 | M39: 3.336166
C40: 69.99 | D40: -0.1787 | E40: =C40*D40 -> -12.507213
C41: 69.99 | D41: -1.0888 | E41: =C41*D41 -> -76.205112
C42: 69.99 | D42: -17.2523 | E42: =C42*D42 -> -1207.4885
A43: 44286 | F43: 0.40705848 | J43: 31.19 | K43: 64.1128 | L43: =J43*K43 -> 1999.6782 | M43: 0.13686722
J44: 31.24 | K44: 64.1537 | L44: =J44*K44 -> 2004.1616
J45: 31.23 | K45: 32.0768 | L45: =J45*K45 -> 1001.7585
A46: 44287 | F46: =0.40705848+0.00026197 -> 0.40732045 | M46: 0.15915413
A47: 44288 | F47: =0.40705848+0.00027962 -> 0.4073381 | J47: 31.65 | K47: -9.4741 | L47: =J47*K47 -> -299.85526 | M47: 0.15918971
J48: 31.65 | K48: -31.6056 | L48: =J48*K48 -> -1000.3172
J49: 31.65 | K49: -6.3191 | L49: =J49*K49 -> -199.99951
A50: 44289 | C50: 73.95 | D50: 27.0453 | E50: =C50*D50 -> 1999.9999 | F50: =0.40705848+0.00037068 -> 0.40742916 | M50: 0.14863015
C51: 73.7 | D51: 27.137 | E51: =C51*D51 -> 1999.9969
A52: 44290 | C52: 74.42 | D52: -28.124 | E52: =C52*D52 -> -2092.9881 | F52: =0.40705848+0.01257322 -> 0.4196317 | J52: 31.65 | K52: -47.3879 | L52: =J52*K52 -> -1499.827 | M52: 0.13807067
C53: 74.4 | D53: 40.3225 | E53: =C53*D53 -> 2999.994 | J53: 31.8 | K53: -100 | L53: =J53*K53 -> -3180
C54: 74.4 | D54: 53.7633 | E54: =C54*D54 -> 3999.9895 | J54: 31.87 | K54: -79.4195 | L54: =J54*K54 -> -2531.0995
A55: 44291 | B55: 9000 | C55: 76.17 | D55: 5.0813 | E55: =C55*D55 -> 387.04262 | F55: =0.02058214+0.40705848 -> 0.42764062 | J55: 31.75 | K55: 31.4959 | L55: =J55*K55 -> 999.99482 | M55: 0.11574836
C56: 76.17 | D56: 8.0472 | E56: =C56*D56 -> 612.95522
C57: 76.1 | D57: 13.1405 | E57: =C57*D57 -> 999.99205
C58: 76 | D58: 13.1578 | E58: =C58*D58 -> 999.9928
C59: 75.8 | D59: 13.1925 | E59: =C59*D59 -> 999.9915
C60: 75.7 | D60: 13.21 | E60: =C60*D60 -> 999.997
C61: 75.7 | D61: 13.21 | E61: =C61*D61 -> 999.997
C62: 75.7 | D62: 3 | E62: =C62*D62 -> 227.1
C63: 75.6 | D63: 13.2275 | E63: =C63*D63 -> 999.999
A64: 44292 | C64: 75.6 | D64: 13.2275 | E64: =C64*D64 -> 999.999 | F64: =0.48840105+0.00314506 -> 0.49154611 | J64: 31.65 | K64: 31.5955 | L64: =J64*K64 -> 999.99757 | M64: 0.11212438
C65: 75.55 | D65: 13.2362 | E65: =C65*D65 -> 999.99491 | J65: 31.92 | K65: -250.8018 | L65: =J65*K65 -> -8005.5935
C66: 75.5 | D66: 6.6225 | E66: =C66*D66 -> 499.99875
C67: 75.4 | D67: 13.2625 | E67: =C67*D67 -> 999.9925
C68: 75.35 | D68: 6.6357 | E68: =C68*D68 -> 499.99999
C69: 75.3 | D69: 13.2802 | E69: =C69*D69 -> 999.99906
C70: 75.2 | D70: 13.2978 | E70: =C70*D70 -> 999.99456
C71: 75.1 | D71: 13.3155 | E71: =C71*D71 -> 999.99405
C72: 75 | D72: 13.3421 | E72: =C72*D72 -> 1000.6575
C73: 75.5 | D73: 0.4213 | E73: =C73*D73 -> 31.80815
C74: 75.5 | D74: 12.8237 | E74: =C74*D74 -> 968.18935
C75: 75.4 | D75: 13.2625 | E75: =C75*D75 -> 999.9925
C76: 75.3 | D76: 13.2802 | E76: =C76*D76 -> 999.99906
C77: 75.2 | D77: 13.2978 | E77: =C77*D77 -> 999.99456
... C80: 74.9 | D80: 13.3511 | E80: =C80*D80 -> 999.99739
A81: 44293 | F81: =0.01919396+0.54046029 -> 0.55965425 | J81: 32.2 | K81: -125.457 | L81: =J81*K81 -> -4039.7154 | M81: 0.05608727
A82: 44294 | B82: =65142 -> 65142 | F82: =0.01931907+0.54046029 -> 0.55977936 | M82: 0.02805618
A83: 44295 | C83: 82.4 | D83: -6.0686 | E83: =C83*D83 -> -500.05264 | J83: 32.21 | K83: -30 | L83: =J83*K83 -> -966.3
C84: 82.6 | D84: -6.0532 | E84: =C84*D84 -> -499.99432 | J84: 32.22 | K84: -30 | L84: =J84*K84 -> -966.6
J85: 32.14 | K85: 31.1138 | L85: =J85*K85 -> 999.99753
J86: 32.12 | K86: 31.1332 | L86: =J86*K86 -> 999.99838
J87: 32.1 | K87: 0.0004 | L87: =J87*K87 -> 0.01284
J88: 32.1 | K88: 0.668 | L88: =J88*K88 -> 21.4428
J89: 32.1 | K89: 14.9079 | L89: =J89*K89 -> 478.54359
A90: 44296 | B90: =80000*0 -> 0 | C90: 92.79 | D90: 10.7759 | E90: =C90*D90 -> 999.89576 | J90: 32.05 | K90: 15.6006 | L90: =J90*K90 -> 499.99923
C91: 92.78 | D91: 21.556 | E91: =C91*D91 -> 1999.9657
C92: 92.79 | D92: 21.554 | E92: =C92*D92 -> 1999.9957
C93: 92.8 | D93: 21.5517 | E93: =C93*D93 -> 1999.9978
C94: 92.8 | D94: 21.5517 | E94: =C94*D94 -> 1999.9978
C95: 92.79 | D95: 21.554 | E95: =C95*D95 -> 1999.9957
C96: 91.95 | D96: 21.7509 | E96: =C96*D96 -> 1999.9953
C97: 91.94 | D97: 21.7533 | E97: =C97*D97 -> 1999.9984
C98: 91.71 | D98: 21.7746 | E98: =C98*D98 -> 1996.9486
C99: 91.6 | D99: 21.8818 | E99: =C99*D99 -> 2004.3729
C100: 91.7 | D100: 21.8818 | E100: =C100*D100 -> 2006.5611
C101: 91.7 | D101: 21.8102 | E101: =C101*D101 -> 1999.9953
C102: 91.65 | D102: 21.8102 | E102: =C102*D102 -> 1998.9048
...

Sheet Binance
B1: THB | C1: =C2-B2 -> -40846 | E1: BNB Spent | F1: BNB Unit | G1: BNB transaction Cost | H1: BNB Avg Cost | I1: USDT Spent | J1: USDT Unit | K1: USDT transaction Cost | L1: USDT Avg Cost | M1: BUSD Spent | N1: BUSD Unit | O1: BUSD transaction Cost | P1: BUSD Avg cost | Q1: LUNA/BNB Price | R1: LUNA/BNB Amount | S1: LUNA/BNB Avg Cost | T1: AXS/BNB Price | U1: AXS/BNB Amount | V1: AXS/BNB Avg Cost | W1: CAKE/BNB Price | X1: CAKE/BNB Amount | Y1: CAKE/BNB Avg Cost | Z1: AXS/USDT Price | AA1: AXS/USDT Amount | AB1: AXS/USDT Avg Cost | AC1: CAKE/USDT Price | AD1: CAKE/USDT Amount | AE1: CAKE/USDT Avg Cost | AF1: BNB/USDT Price | AG1: BNB/USDT Amount | AH1: BNB/USDT Avg Cost | AI1: AXS/BUSD Price | AJ1: AXS/BUSD Amount | AK1: AXS/BUSD Avg Cost | AL1: CAKE/BUSD Price | AM1: CAKE/BUSD Amount | AN1: CAKE/BUSD Avg Cost | AO1: Total AXS | AP1: Total THB4AXS | AQ1: THB/AXS Avg Cost
A2: Date\Total | B2: =SUM(B3:B1000) -> 120000 | C2: 79154 | D2: =(C2-B2)/B2 -> -0.34038333 | E2: 5000 | F2: 0.32153885 | G2: =E2/F2 -> 15550.22 | H2: =SUM(E2:E200)/SUM(F2:F200) -> 15172.002 | I2: 30000 | J2: 890.47 | K2: =I2/J2 -> 33.690074 | L2: =SUM(I2:I200)/SUM(J2:J200) -> 33.690074 | M2: 7970.71 | N2: 236.30922 | O2: =M2/N2 -> 33.73 | P2: =SUM(M2:M200)/SUM(N2:N200) -> 34.019476 | Q2: 0.15985 | R2: 0.92 | S2: =SUMPRODUCT(Q2:Q200,R2:R200)/SUM(R2:R200) -> 0.15992459 | T2: 0.1618 | U2: 0.47 | V2: =SUMPRODUCT(T2:T200,U2:U200)/SUM(U2:U200) -> 0.1604205 | W2: 0.02348 | X2: 4.99 | Y2: =SUMPRODUCT(W2:W200,X2:X200)/SUM(X2:X200) -> 0.02348 | Z2: 72.35 | AA2: 2 | AB2: =SUMPRODUCT(Z2:Z200,AA2:AA200)/SUM(AA2:AA200) -> 72.311429 | AC2: 10.72 | AD2: 5 | AE2: =SUMPRODUCT(AC2:AC200,AD2:AD200)/SUM(AD2:AD200) -> 10.7335 | AF2: 470 | AG2: 0.247 | AH2: =SUMPRODUCT(AF2:AF200,AG2:AG200)/SUM(AG2:AG200) -> 469.84211 | AI2: 63.5 | AJ2: 1 | AK2: =SUMPRODUCT(AI2:AI201,AJ2:AJ201)/SUM(AJ2:AJ201) -> 42.099495 | AL2: 7.6 | AM2: 5 | AN2: =SUMPRODUCT(AL2:AL200,AM2:AM200)/SUM(AM2:AM200) -> 6.8412492 | AO2: =SUM(U2:U100)+SUM(AA2:AA100)+SUM(AJ2:AJ100) -> 39.09 | AP2: =SUM(T2:T100)*H2+SUM(Z2:Z100)*L2+SUM(AI2:AI100)*P2 -> 83133.542 | AQ2: =AP2/AO2 -> 2126.7215
A3: 44568 | B3: 5000 | E3: 1376.86 | F3: 0.09234275 | G3: =E3/F3 -> 14910.321 | M3: 10000 | N3: 296.55991 | O3: =M3/N3 -> 33.72 | Q3: 0.16 | R3: 0.91 | T3: 0.1615 | U3: 0.53 | W3: 0.02348 | X3: 0.01 | Z3: 72.32 | AA3: 1.46 | AC3: 10.76 | AD3: 2 | AF3: 469.5 | AG3: 0.114 | AI3: 62.85 | AJ3: 2 | AL3: 7.6 | AM3: 4.71
A4: 44571 | B4: 1376.86 | E4: 3000 | F4: 0.20107238 | G4: =E4/F4 -> 14920 | M4: 5000 | N4: 151.97568 | O4: 32.9 | T4: 0.1592 | U4: 1 | Z4: 72.32 | AA4: 0.54 | AC4: 10.75 | AD4: 3 | AI4: 52.7 | AJ4: 0.38 | AL4: 7.58 | AM4: 3.74
A5: 44571 | B5: 3000 | E5: 2240 | F5: 0.15013404 | G5: =E5/F5 -> 14920.001 | M5: 5000 | N5: 148.85383 | O5: 33.59 | Z5: 72.28 | AA5: 3 | AC5: 10.74 | AD5: 5 | AI5: 53.15 | AJ5: 1 | AL5: 7.58 | AM5: 2
A6: 44571 | B6: 2240 | E6: 412.43 | F6: 0.02777306 | G6: =E6/F6 -> 14850.002 | M6: 5000 | N6: 148.98689 | O6: 33.56 | AC6: 10.72 | AD6: 5 | AI6: 53 | AJ6: 1 | AL6: 6.39 | AM6: 12.44
A7: 44571 | B7: 412.43 | M7: 5000 | N7: 149.16468 | O7: 33.52 | AI7: 48.3 | AJ7: 1.5 | AL7: 8.91 | AM7: 1.97
A8: 44580 | B8: 30000 | M8: 30000 | N8: 869.81734 | O8: 34.49 | AI8: 65.62 | AJ8: 2 | AL8: 7.5 | AM8: 2.42
A9: 44582 | B9: 7970.71 | M9: 10000 | N9: 290.27576 | O9: 34.45 | AI9: 64.52 | AJ9: 0.2 | AL9: 7.2 | AM9: 8
A10: 44592 | B10: 10000 | AI10: 64.43 | AJ10: 0.2 | AL10: 5.3 | AM10: 9.43
A11: 44620 | B11: 5000 | AI11: 64.16 | AJ11: 0.2
A12: 44651 | B12: 5000 | AI12: 64.3 | AJ12: 0.2
A13: 44656 | B13: 5000 | AI13: 64.26 | AJ13: 0.2
A14: 44656 | B14: 5000 | AI14: 64 | AJ14: 0.2
A15: 44680 | B15: 30000 | AI15: 63.95 | AJ15: 0.2
A16: 44683 | B16: 10000 | AI16: 63.82 | AJ16: 0.2
AI17: 64.19 | AJ17: 0.2
AI18: 63.82 | AJ18: 0.4
AI19: 63.67 | AJ19: 0.2
AI20: 63.3 | AJ20: 0.2
AI21: 62.39 | AJ21: 0.2
AI22: 62.35 | AJ22: 0.2
AI23: 62.29 | AJ23: 0.2
AI24: 62.37 | AJ24: 0.2
AI25: 62.31 | AJ25: 0.2
AI26: 62.18 | AJ26: 0.2
AI27: 62.07 | AJ27: 0.2
AI28: 61.98 | AJ28: 0.2
... AI36: 23.2 | AJ36: 3

Sheet Fund
L1: 10 | N1: 10 | AD1: 10 | AG1: 15 | AK1: 15 | AQ1: =400000*0.2 -> 80000 | AR1: =400000*0.25 -> 100000 | AS1: 100000 | AV1: =400000*0.25 -> 100000 | AW1: =400000*0.15 -> 60000 | AX1: =400000*0.15 -> 60000 | BB1: 10 | BD1: 10 | BF1: =AK1+AS1 -> 100015 | BG1: =N1+AG1 -> 25 | BH1: =BD1+BB1+AV1+AD1+O1+L1 -> 100040 | BI1: =SUM(L1:BD1) -> 500080
B2: Aberdeen | F2: Krungsri | L2: =L1/100*$BI$2 -> 3350 | N2: =N1/100*$BI$2 -> 3350 | P2: Bualuang | AA2: 5000 | AD2: =AD1/100*$BI$2 -> 3350 | AG2: =AG1/100*$BI$2 -> 5025 | AK2: =AK1/100*$BI$2 -> 5025 | AQ2: 20 | AR2: 25 | AS2: 100 | AV2: 25 | AW2: 15 | AX2: 15 | BB2: =BB1/100*$BI$2 -> 3350 | BD2: =BD1/100*$BI$2 -> 3350 | BE2: One | BF2: =BF1/100*$BI$2 -> 33505025 | BG2: =BG1/100*$BI$2 -> 8375 | BH2: =BH1/100*$BI$2 -> 33513400 | BI2: 33500 | BK2: =AA235 -> 18.8296 | BL2: =AY235 -> 10.9681 | BM2: =BA235 -> 21.6797 | BN2: Nav
F3: 5 | J3: THA | L3: Non-Asia1 | N3: Asia1 | O3: Non-Asia4.2 | AA3: Buffer | AD3: Non-Asia2 | AG3: Asia2 | AK3: THA1 | AQ3: Tisco | AR3: KKP | AS3: Kbank | AT3: Tisco | AX3: SCB | AY3: Buffer | AZ3: Buffer | BA3: Buffer | BB3: Non-Asia3 | BD3: Non-Asia4.1 | BF3: THA | BG3: Asia | BH3: Non-Asia | BI3: 5000 Total | BK3: 1.2 | BL3: 0.348 | BM3: 0.6624 | BN3: Yield | BP3: =35000*0.3 -> 10500
A4: Date | B4: ABLTF | C4: ABAGS | D4: ABSC-RMF | E4: ABGDD-RMF | F4: KFSMART | G4: KFGBRANRMF | H4: KFAFIXRMF | I4: KF-HCHINAD | J4: KFFLEX2RMF | K4: KFLTFDIV | L4: KFGTECHRMF | M4: KFGOLDRMF | N4: KF-GCHINARMF | O4: KFEURORMF | P4: B-LTF | Q4: BLTF75 | R4: ESGXBMDIV-SW | S4: BERMF | T4: BGOLDRMF | U4: B-INNOTECHRMF | V4: MEGA10CHINA-A | W4: KT-BLOCKCHAIN-A | X4: ASP-USSMALL-A | Y4: MATECH-D | Z4: MATECH-A | AA4: K-USXNDQ-A(D) | AB4: K-USXNDQ-A(A) | AC4: K-WORLDX | AD4: KCHANGERMF | AE4: K-EUROPE-A(D) | AF4: K-VIETNAM | AG4: KVIETNAMRMF | AH4: K-CHX | AI4: KMSRMF | AJ4: KGDRMF | AK4: KBLRMF | AL4: KDLTF | AM4: K70LTF-C(L) | AN4: K-70ThaiESGX-L | AO4: KCHINARMF | AP4: KUSARMF | AQ4: TCHRMF | AR4: KKP TECH RMF-H | AS4: K-HDThaiESGX-68 | AT4: TDSThaiESG-A | AU4: KT-GOLD RMF | AV4: ES-EGRMF | AW4: DAOL-GOLDRMF | AX4: SCBRMJP | AY4: SCBBLN | AZ4: SCBGOLDHE | BA4: SCBS&P500 | BB4: SCBRMS&P500 | BC4: SCBAUD | BD4: TEURMF-A | BK4: K-USXNDQ-A(D) | BL4: SCBBLN | BM4: SCBS&P500
A5: 43421 | B5: 48.2341 | D5: 91.6912 | F5: 10.3811 | I5: 8.5733 | J5: 59.1984 | K5: 25.7371 | P5: 41.3142 | Q5: 29.304 | S5: 97.1006 | AA5: 14.0905 | AI5: 15.0135 | AK5: 27.0278 | BK5: =BK3/BK2 -> 0.063729447 | BL5: =BL3/BL2 -> 0.031728376 | BM5: =BM3/BM2 -> 0.030553928
A6: 43428 | B6: 47.9819 | D6: 91.2329 | F6: 10.383 | I6: 8.476 | J6: 58.4192 | K6: 25.4715 | P6: 41.3066 | Q6: 29.3155 | S6: 97.0854
A7: 43436 | B7: 48.4711 | D7: 92.1298 | F7: 10.3886 | I7: 8.6087 | J7: 59.1966 | K7: 25.7639 | P7: 41.7102 | Q7: 29.5582 | S7: 98.0255 | AA7: 14.0774 | AI7: 15.1097 | AK7: 27.0753 | BK7: M3, M6, M9, M12 | BL7: M6, M12 | BM7: M6, M12
A8: 43443 | B8: 48.4747 | D8: 92.0829 | F8: 10.3929 | I8: 8.5192 | J8: 59.4869 | K8: 25.879 | P8: 41.9935 | Q8: 29.7264 | S8: 98.6937 | AA8: 13.7692 | AI8: 15.1323 | AK8: 27.1333
A9: 43449 | B9: 47.2962 | D9: 89.9181 | F9: 10.3951 | I9: 8.661 | J9: 58.1046 | K9: 25.2445 | P9: 41.4408 | Q9: 29.4477 | S9: 97.3972 | AA9: 13.6122 | AI9: 14.6389 | AK9: 26.8542
A10: 43456 | B10: 46.7687 | D10: 88.8176 | F10: 10.395 | I10: 8.2104 | J10: 57.4337 | K10: 24.9663 | P10: 41.3334 | Q10: 29.4072 | S10: 97.1482 | AA10: 12.5765 | AI10: 14.3105 | AK10: 26.8015 | AL10: 19.0223
A11: 43462 | B11: 45.2787 | D11: 86.0301 | F11: 10.3973 | I11: 8.1485 | J11: 55.7475 | K11: 24.2693 | P11: 39.9374 | Q11: 28.5942 | S11: 93.8696 | AA11: 12.6573 | AI11: 13.9839 | AK11: 26.6411 | AL11: 18.7172
A12: 43470 | B12: 46.1658 | D12: 87.6749 | F12: 10.4012 | I12: 7.9857 | J12: 56.4273 | K12: 24.7019 | P12: 40.4308 | Q12: 28.888 | S12: 95.045 | AA12: 12.3773 | AI12: 13.9951 | AK12: 26.7361 | AL12: 18.9009
A13: 43476 | B13: 46.16 | D13: 87.6932 | F13: 10.4045 | I13: 8.3978 | J13: 57.4018 | K13: 25.0007 | P13: 40.574 | Q13: 28.9763 | S13: 95.3733 | AA13: 13.259 | AI13: 14.2828 | AK13: 26.8546 | AL13: 19.1421
A14: 43485 | B14: 46.1529 | D14: 87.6751 | F14: 10.4084 | I14: 8.4983 | J14: 56.6865 | K14: 24.732 | P14: 40.6521 | Q14: 29.0243 | S14: 95.5659 | AA14: 13.4271 | AI14: 14.0287 | AK14: 26.7415 | AL14: 19.0589
A15: 43491 | B15: 47.4618 | D15: 90.1831 | F15: 10.4103 | I15: 8.5661 | J15: 58.273 | K15: 25.3713 | P15: 41.7229 | Q15: 29.664 | S15: 98.0929 | AA15: 13.3919 | AI15: 14.6134 | AK15: 26.9969 | AL15: 19.5485
A16: 43498 | B16: 48.3227 | D16: 91.8439 | F16: 10.4139 | I16: 8.7317 | J16: 59.1671 | K16: 25.7998 | P16: 42.3182 | Q16: 29.9658 | S16: 99.4871 | AA16: 13.747 | AI16: 14.9491 | AK16: 27.1587 | AL16: 19.8325
A17: 43505 | B17: 48.422 | D17: 92.0595 | F17: 10.4174 | I17: =AVERAGE(I16,I18) -> 8.86475 | J17: 59.1368 | K17: 25.7443 | P17: 42.299 | Q17: 29.9496 | S17: 99.451 | AA17: 13.7519 | AI17: 14.9442 | AK17: 27.1347 | AL17: 19.7894
A18: 43512 | B18: 48.0141 | D18: 91.2661 | F18: 10.4208 | I18: 8.9978 | J18: 58.5261 | K18: 25.4621 | P18: 41.9195 | Q18: 29.7488 | S18: 98.5594 | AA18: 13.9833 | AI18: 14.8736 | AK18: 27.0264 | AL18: 19.5658
A19: 43519 | B19: 48.3709 | D19: 91.9105 | F19: 10.4239 | I19: 9.0725 | J19: 59.2303 | K19: 25.8089 | P19: 42.4988 | Q19: 30.0776 | S19: 99.9176 | AA19: 13.9938 | AI19: 14.9305 | AK19: 27.1501 | AL19: 19.8298
A20: 43499 | B20: 47.941 | D20: 91.0804 | F20: 10.4285 | I20: 9.1271 | J20: 58.4126 | K20: 25.4849 | P20: 42.0383 | Q20: 29.8191 | S20: 98.8479 | AA20: 13.8815 | AI20: 14.7304 | AK20: 27.035 | AL20: 19.4769
A21: 43533 | B21: 47.5609 | D21: 90.3317 | F21: 10.4325 | I21: 9.1818 | J21: 58.1607 | K21: 25.4831 | P21: 41.8893 | Q21: 29.7316 | S21: 98.5035 | AA21: 13.7653 | AI21: 14.7457 | AK21: 26.9803 | AL21: 19.3837
A22: 43540 | B22: 47.4933 | D22: 90.2195 | F22: 10.4373 | I22: 8.7978 | J22: 58.0386 | K22: 25.4135 | P22: 41.7515 | Q22: 29.6443 | S22: 98.1887 | AA22: 14.1601 | AI22: 14.7052 | AK22: 26.9675 | AL22: 19.3273
A23: 43547 | B23: 48.1294 | D23: 91.3011 | F23: 10.4408 | I23: 8.9952 | J23: 58.746 | K23: 25.74 | P23: 42.0112 | Q23: 29.7991 | S23: 98.7995 | AA23: 14.6297 | AI23: 14.8253 | AK23: 27.1533 | AL23: 19.648
A24: 43554 | B24: 47.9928 | D24: 91.0871 | F24: 10.4441 | I24: 8.9473 | J24: 58.4463 | K24: 25.5865 | P24: 41.9024 | Q24: 29.7367 | S24: 98.5478 | AA24: 14.3014 | AI24: 14.8618 | AK24: 27.0988 | AL24: 19.5594
A25: 43561 | B25: 48.1997 | D25: 91.5568 | F25: 10.4456 | I25: 9.3821 | J25: 58.539 | K25: 25.6549 | P25: 42.1348 | Q25: 29.8725 | S25: 99.0887 | AA25: 14.714 | AI25: 15.0109 | AK25: 27.1682 | AL25: 19.6278
A26: 43569 | B26: 48.4503 | D26: 92.0131 | F26: 10.4507 | I26: 9.4237 | J26: 58.98 | K26: 25.8767 | P26: 42.4513 | Q26: 30.0499 | S26: 99.8218 | AA26: 14.8149 | AI26: 15.171 | AK26: 27.2635 | AL26: 19.7986
A27: 43575 | B27: 48.8735 | D27: 92.7092 | F27: 10.4545 | I27: 9.4544 | J27: 59.6011 | K27: 26.112 | P27: 42.7096 | Q27: 30.2072 | S27: 100.4164 | AA27: 14.9982 | AI27: 15.3461 | AK27: 27.3409 | AL27: 19.9615
A28: 43583 | B28: 48.9332 | D28: 92.9118 | F28: 10.458 | I28: 9.3403 | J28: 59.3475 | K28: 25.9178 | P28: 42.4686 | Q28: 30.0583 | S28: 99.8566 | AA28: 15.254 | AI28: 15.2462 | AK28: 27.3224 | AL28: 19.9135
A29: 43589 | B29: 49.2265 | D29: 93.5105 | F29: 10.4624 | I29: 9.3845 | J29: 59.8265 | K29: 26.0399 | P29: 42.9671 | Q29: 30.3627 | S29: 101.0215 | AA29: 15.0567 | AI29: 15.4539 | AK29: 27.4159 | AL29: 20.1108
... A39: 43666 | B39: 51.2471 | D39: 97.3153 | F39: 10.5094 | I39: 8.867 | J39: 59.2033 | K39: 26.4153 | P39: 44.7056 | Q39: 31.3593 | S39: 105.0352 | AA39: 15.104 | AI39: 15.8514 | AK39: 27.7441 | AL39: 20.6266
A40: 43673 | F40: 10.5132 | I40: 9.1075 | J40: 58.5275 | K40: 26.2664 | P40: 44.4349 | Q40: 31.2175 | S40: 104.3916 | AA40: 15.167 | AI40: 15.7468
A41: 43681 | B41: 49.7505 | D41: 94.585 | F41: 10.5182 | I41: 8.8542 | J41: 57.6305 | K41: 25.8618 | P41: 43.4358 | Q41: 30.6891 | S41: 102.0818 | AA41: 14.924 | AI41: 15.2721 | AK41: 27.484 | AL41: 19.8682
A42: 43689 | B42: 48.5732 | D42: 92.3948 | F42: 10.5299 | I42: 8.4355 | J42: 56.377 | K42: 25.3787 | P42: 42.6532 | Q42: 30.2331 | S42: 100.2573 | AA42: 14.7793 | AI42: 14.9737 | AK42: 27.4535 | AL42: 19.531
A43: 43695 | B43: 47.9374 | D43: 91.196 | F43: 10.5329 | I43: 8.2851 | J43: 55.7244 | K43: 25.1591 | P43: 42.0398 | Q43: 29.9009 | S43: 98.8312 | AA43: 14.3486 | AI43: 14.8809 | AK43: 27.4127 | AL43: 19.2977
A44: 43701 | B44: 48.2476 | D44: 91.8151 | F44: 10.5338 | I44: 8.6027 | J44: 55.9276 | K44: 25.2635 | P44: 42.7938 | Q44: 30.308 | S44: 100.6132 | AA44: 14.7534 | AI44: 14.8773 | AK44: 27.5155 | AL44: 19.5613
A45: 43708 | B45: 48.5372 | D45: 92.3472 | F45: 10.5404 | I45: 8.5169 | J45: 56.342 | K45: 25.4916 | P45: 42.8592 | Q45: 30.3246 | S45: 100.7646 | AA45: 14.736 | AI45: 15.1046 | AK45: 27.5613 | AL45: 19.644
A46: 43715 | B46: 48.8299 | D46: 92.9628 | F46: 10.5404 | I46: 8.7607 | J46: 56.8634 | K46: 25.752 | P46: 43.2994 | Q46: 30.5675 | S46: 101.8006 | AA46: 14.8135 | AI46: 15.2393 | AK46: =27.6409 -> 27.6409 | AL46: 19.5057
A47: 43722 | B47: 48.6606 | D47: 92.5334 | F47: 10.5451 | I47: 8.8869 | J47: 56.7659 | K47: 25.6569 | P47: 43.1652 | Q47: 30.5053 | S47: 101.4764 | AA47: 14.9165 | AI47: 15.097 | AK47: 27.512 | AL47: 19.3133
A48: 43729 | B48: 47.5682 | D48: 90.5247 | F48: 10.5451 | I48: 8.8028 | J48: 55.9008 | K48: 25.3677 | P48: 42.4842 | Q48: 30.122 | S48: 99.9018 | AA48: 14.8865 | AI48: 14.6298 | AK48: 27.4594 | AL48: 19.1277
A49: 43736 | B49: 47.7525 | D49: 90.8708 | F49: 10.5533 | I49: 8.6404 | J49: 56.0331 | K49: 25.4431 | P49: 42.8069 | Q49: 30.3039 | S49: 100.6511 | AA49: 14.6504 | AI49: 14.8311 | AK49: 27.5099 | AL49: 19.195
A50: 43743 | B50: 46.3051 | D50: 88.1045 | F50: 10.5542 | I50: 8.6406 | J50: 54.8013 | K50: 24.8605 | P50: 41.9314 | Q50: 29.8189 | S50: 98.6109 | AA50: 14.3949 | AI50: 14.4586 | AK50: 27.3044 | AL50: 18.7547
A51: 43751 | F51: 10.5573 | I51: 8.6639 | J51: 55.5703 | K51: 25.1875 | P51: 42.3203 | Q51: 30.034 | S51: 99.5253 | AA51: 14.5743 | AI51: 14.7862 | AK51: 27.4728 | AL51: 19.1303
A52: 43757 | B52: 46.8883 | D52: 89.3283 | F52: 10.559 | I52: 8.9867 | J52: 55.7843 | K52: 25.2349 | P52: 42.6605 | Q52: 30.2091 | S52: 100.3241 | AA52: 14.9332 | AI52: 14.8696 | AK52: 27.5387 | AL52: 19.3345
A53: 43766 | B53: 46.2218 | D53: 88.0652 | F53: 10.5629 | I53: 8.9212 | J53: 54.8786 | K53: 24.7843 | P53: 41.7388 | Q53: 29.6816 | S53: 98.1689 | AA53: 15.0785 | AI53: 14.5255 | AK53: 27.4242 | AL53: 19.05
A54: 43771 | B54: 46.2886 | D54: 88.0828 | F54: 10.5669 | I54: 9.1538 | J54: 54.8821 | K54: 24.9037 | P54: 41.508 | Q54: 29.5641 | S54: 97.6284 | AA54: 15.181 | AI54: 14.407 | AK54: 27.3881 | AL54: 18.9148
A55: 43779 | B55: 47.6324 | D55: 90.6052 | F55: 10.5764 | I55: 9.4812 | J55: 56.2049 | K55: 24.7315 | P55: 42.4019 | Q55: 30.0387 | S55: 99.7349 | AA55: 15.44 | AI55: 14.8806 | AK55: 27.6621 | AL55: 19.5121
A56: 43785 | B56: 46.8985 | D56: 89.2019 | F56: 10.5824 | I56: 9.1501 | J56: 55.0193 | K56: 24.2236 | P56: 41.5407 | Q56: 29.5695 | S56: 97.73 | AA56: 15.5116 | AI56: 14.4063 | AK56: 27.4737 | AL56: 19.1458
A57: 43792 | B57: 46.7222 | D57: 88.9618 | F57: 10.5847 | I57: 9.143 | J57: 54.6925 | K57: 23.9676 | P57: 41.3971 | Q57: 29.4569 | S57: 97.386 | AA57: 15.5254 | AI57: 14.4314 | AK57: 27.4418 | AL57: 19.0218
A58: 43799 | B58: 46.6248 | D58: 88.7275 | F58: 10.5897 | I58: 9.2322 | J58: 54.378 | K58: 23.7521 | P58: 41.3617 | Q58: 29.4332 | S58: 97.2934 | AA58: 15.8486 | AI58: 14.4538 | AK58: 27.4259 | AL58: 18.8185
A59: 43807 | B59: 45.624 | D59: 86.8644 | F59: 10.5931 | I59: 9.0126 | J59: 53.384 | K59: 23.2437 | P59: 40.5138 | Q59: 28.9273 | S59: 95.3182 | AA59: 15.3766 | AI59: 14.1447 | AK59: 27.2403 | AL59: 18.5203
A60: 43813 | B60: 46.3183 | D60: 88.0821 | F60: 10.5966 | I60: 9.3259 | J60: 53.8962 | K60: 23.5561 | P60: 40.7486 | Q60: 29.0172 | S60: 95.8754 | AA60: 15.6702 | AI60: 14.282 | AK60: 27.3533 | AL60: 18.6871
A61: 43820 | B61: 46.0046 | D61: 87.415 | F61: 10.6001 | I61: 9.5575 | J61: 54.0081 | K61: 23.6195 | P61: 40.4441 | Q61: 28.8548 | S61: 95.1603 | AA61: 15.9855 | AI61: 14.2027 | AK61: 27.3767 | AL61: 18.6845
A62: 43829 | B62: 46.1652 | D62: 87.6702 | F62: 10.6039 | I62: 9.5757 | J62: 54.0089 | K62: 23.6847 | P62: 40.7248 | Q62: 29.0315 | S62: 95.8045 | AA62: 16.2112 | AI62: 14.3285 | AK62: 27.3949 | AL62: 18.6821
A63: 43835 | B63: 46.4482 | D63: 88.2447 | F63: 10.6108 | I63: 9.8109 | J63: 54.4638 | K63: 23.942 | P63: 40.8046 | Q63: 29.059 | S63: 95.995 | AA63: 16.3983 | AI63: 14.4604 | AK63: 27.5495 | AL63: 18.9214
... A81: 43961 | B81: 35.7384 | D81: 68.7286 | F81: 10.6502 | I81: 8.5465 | J81: 44.5582 | K81: 18.7121 | P81: 34.2591 | Q81: 25.2069 | S81: 80.6609 | AA81: 16.4168 | AI81: 11.7527 | AK81: 25.6757 | AL81: 15.4624
A82: 43967 | B82: =36.1264 -> 36.1264 | D82: 69.6429 | F82: 10.6504 | I82: 8.591 | J82: 44.7528 | K82: 18.7482 | P82: 34.1668 | Q82: 25.1333 | S82: 80.4468 | AA82: 16.3972 | AI82: 11.9137 | AK82: 25.7004 | AL82: 15.4961
A83: 43974 | B83: 36.9293 | D83: 71.2479 | F83: 10.654 | I83: 8.7767 | J83: 45.2685 | K83: 19.0567 | P83: 34.6948 | Q83: 25.4521 | S83: 81.6636 | AA83: 16.8999 | AI83: 12.3837 | AK83: 25.851 | AL83: 15.7218
A84: 43981 | B84: 38.2244 | D84: 73.6764 | F84: 10.6538 | I84: 8.5422 | J84: 46.5024 | K84: 19.8141 | P84: 35.9861 | Q84: 26.2229 | S84: 84.6502 | AA84: 16.9848 | AI84: 12.6792 | AK84: 26.011 | AL84: 16.167
A85: 43988 | B85: 40.9156 | D85: 78.9148 | F85: 10.6537 | I85: 9.0009 | J85: 49.3794 | K85: 21.1838 | P85: 38.0013 | Q85: 27.443 | S85: 89.3201 | AA85: 17.0838 | AI85: 13.4024 | AK85: 26.723 | AL85: 17.2926
A86: 43995 | B86: 39.4876 | D86: 76.2458 | F86: 10.6593 | I86: 9.0829 | J86: 47.6876 | K86: 20.3922 | P86: 36.4883 | Q86: 26.5345 | S86: 85.8079 | AA86: 16.9849 | AI86: 13.2735 | AK86: 26.3204 | AL86: 16.6998
A87: 44002 | B87: 39.05 | D87: 75.3976 | F87: 10.6596 | I87: 9.1684 | J87: 47.4882 | K87: 20.2669 | P87: 36.2984 | Q87: 26.3902 | S87: 85.3509 | AA87: 17.7047 | AI87: 13.2943 | AK87: 26.2602 | AL87: 16.5336
A88: 44009 | B88: 37.8931 | D88: 73.2497 | F88: 10.6638 | I88: 9.2983 | J88: 46.2956 | K88: 19.686 | P88: 35.4663 | Q88: 25.9094 | S88: 83.414 | AA88: 17.8412 | AI88: 12.8478 | AK88: 26.0056 | AL88: 16.0624
A89: 44016 | B89: 39.0465 | D89: 75.5215 | F89: 10.6653 | I89: 9.4585 | J89: 47.3475 | K89: 20.2611 | P89: 36.4994 | Q89: 26.5016 | S89: 85.8179 | AA89: 18.1511 | AI89: 13.34 | AK89: 26.4651 | AL89: 16.6949
A90: 44023 | B90: 38.5739 | D90: 74.7496 | F90: 10.668 | I90: 10.1626 | J90: 46.4633 | K90: 19.8501 | P90: 36.1145 | Q90: 26.2634 | S90: 84.9272 | AA90: 18.9774 | AI90: 13.214 | AK90: 26.2355 | AL90: 16.2818
A91: 44030 | B91: 38.7642 | D91: 75.1067 | F91: 10.6703 | I91: 9.7437 | J91: 46.7634 | K91: 20.0361 | P91: 36.042 | Q91: 26.2188 | S91: 84.7704 | AA91: 18.7933 | AI91: 13.3649 | AK91: 26.3429 | AL91: 16.4373
A92: 44037 | B92: 38.1551 | D92: 73.9205 | F92: 10.6735 | I92: 10.1685 | J92: 46.1613 | K92: 19.7164 | P92: 35.3683 | Q92: 25.8164 | S92: 83.1978 | AA92: 18.7053 | AI92: 13.2179 | AK92: 26.1816 | AL92: 16.0992
A93: 44044 | B93: 37.3552 | D93: 73.4459 | F93: 10.676 | I93: 10.1976 | J93: 45.7998 | K93: 19.5567 | P93: 35.0306 | Q93: 25.6074 | S93: 82.4315 | AA93: 18.9027 | AI93: 13.1785 | AK93: 26.1041 | AL93: 15.9331
A94: 44051 | B94: 37.7706 | D94: 73.19 | F94: 10.6768 | I94: 10.3829 | J94: 45.6845 | K94: 19.4448 | P94: 34.7469 | Q94: 25.4412 | S94: 81.7633 | AA94: 19.8244 | AI94: 13.2937 | AK94: 26.1302 | AL94: 15.8576
... A99: 44086 | B99: 36.7154 | D99: 71.1289 | F99: 10.6855 | I99: 9.7811 | J99: 44.2433 | K99: 18.4929 | P99: 33.7806 | Q99: 24.8668 | S99: 79.4644 | AA99: 19.3023 | AI99: 12.7158 | AK99: 25.7885 | AL99: 14.892
A100: 44093 | B100: 36.8621 | D100: 71.374 | I100: 10.0184 | J100: 44.1302 | K100: 18.4526 | P100: 33.7885 | Q100: 24.8581 | S100: 79.4856 | AA100: 19.1617 | AI100: 12.802 | AK100: 25.918 | AL100: 14.9023
A101: 44100 | B101: 35.6477 | D101: 69.1265 | F101: 10.6896 | I101: 9.7437 | J101: 42.5135 | K101: 17.5365 | P101: 32.5705 | Q101: 24.1285 | S101: 76.6345 | AA101: 18.8695 | AI101: 12.5823 | AK101: 25.5345 | AL101: 14.2666
A102: 44078 | B102: 35.2827 | D102: 68.4097 | F102: 10.6913 | I102: 9.938 | J102: 42.1168 | K102: 17.4828 | P102: 32.2677 | Q102: 23.9566 | S102: 75.9247 | AA102: 20.0545 | AI102: 12.6453 | AK102: 25.5065 | AL102: 14.2455
A103: 44114 | B103: 36.0136 | D103: 69.7479 | F103: 10.6931 | I103: 10.2493 | J103: 43.0529 | K103: 17.9577 | P103: 32.8339 | Q103: 24.2792 | S103: 77.2285 | AA103: 19.9709 | AI103: 12.897 | AK103: 25.7775 | AL103: 14.5903
A104: 44121 | B104: 34.9776 | D104: 67.7534 | F104: 10.6946 | I104: 10.2572 | J104: 42.1897 | K104: 17.4506 | P104: 31.8123 | Q104: 23.6632 | S104: 74.8519 | AA104: 20.5688 | AI104: 12.5575 | AK104: 25.5759 | AL104: 14.1304
A105: 44128 | B105: 34.6125 | D105: 67.0459 | F105: 10.6964 | I105: 10.4041 | J105: 41.6688 | K105: 17.214 | P105: 31.3373 | Q105: 23.3661 | S105: 73.749 | AA105: 20.1573 | AI105: 12.4712 | AK105: 25.5152 | AL105: 13.9108
A106: 44135 | B106: 33.9984 | D106: 65.9797 | F106: 10.699 | I106: 10.3242 | J106: 41.118 | K106: 16.9426 | P106: 30.6721 | Q106: 22.9509 | S106: 72.2071 | AA106: 19.6113 | AI106: 12.4197 | AK106: 25.2967 | AL106: 13.7556
A107: 44142 | B107: 35.3911 | D107: 68.5452 | F107: 10.7032 | I107: 10.8083 | J107: 42.9394 | K107: 17.4007 | P107: 32.3323 | Q107: 23.9693 | S107: 76.0787 | AA107: 20.8332 | AI107: 12.7741 | AK107: 25.8084 | AL107: 14.5187
A108: 44149 | B108: 38.1026 | D108: 73.639 | F108: 10.7059 | I108: 10.85 | J108: 45.3562 | K108: 18.6189 | P108: 34.8322 | Q108: 25.4873 | S108: 81.8713 | AA108: 20.3795 | AI108: 13.0015 | AK108: 26.5163 | AL108: 15.6377
A109: 44156 | B109: 39.3088 | D109: 75.9625 | F109: 10.7089 | I109: 11.1218 | J109: 46.3896 | K109: 19.1502 | P109: 35.8925 | Q109: 26.1024 | S109: 84.3125 | AA109: 20.4905 | AI109: 13.2592 | AK109: 26.7693 | AL109: 15.9046
A110: 44163 | B110: 40.3023 | D110: 77.9296 | F110: 10.7123 | I110: 10.7761 | J110: 47.4855 | K110: 19.6739 | P110: 37.2202 | Q110: 26.8871 | S110: 87.3816 | AA110: 20.9138 | AI110: 13.7759 | AK110: 27.2244 | AL110: 16.6166
A111: 44170 | B111: 40.5944 | D111: 78.4824 | F111: 10.7201 | I111: 10.7804 | J111: 47.688 | K111: 19.8166 | P111: 37.3095 | Q111: 26.949 | S111: 87.6 | AA111: 21.0978 | AI111: 13.8832 | AK111: 27.3833 | AL111: 16.7299 | AO111: 10.0919 | AP111: 10.1116
A112: 44177 | B112: 41.3574 | D112: 79.8802 | F112: 10.7225 | I112: 10.7804 | J112: 48.3391 | K112: 20.1602 | P112: 38.0602 | Q112: 27.3905 | S112: 89.3249 | AA112: 21.3567 | AI112: 14.0051 | AK112: 27.6133 | AL112: 17.0329 | AO112: 10.2155 | AP112: 10.1676
A113: 44184 | B113: 40.918 | D113: 79.0872 | F113: 10.7261 | I113: 10.9623 | J113: 47.8653 | K113: 19.9045 | P113: 37.7354 | Q113: 27.1619 | S113: 88.5464 | AA113: 21.5082 | AI113: 14.3251 | AK113: 27.5523 | AL113: 16.8883 | AO113: 10.4819 | AP113: 10.5942
A114: 44191 | B114: 40.0887 | D114: 77.4389 | F114: 10.7263 | I114: 10.9054 | J114: 46.4304 | K114: 19.2401 | P114: 36.4642 | Q114: 26.4028 | S114: 85.6714 | AA114: 21.3767 | AI114: 14.2029 | AK114: 27.335 | AL114: 16.3603 | AO114: 10.5587 | AP114: 10.766
A115: 44196 | B115: 39.3183 | D115: 76.053 | F115: 10.7301 | I115: 10.9033 | J115: 46.1756 | K115: 19.1129 | P115: 36.0623 | Q115: 26.1987 | S115: 84.7452 | AA115: 21.6761 | AI115: 14.0345 | AK115: 27.2055 | AL115: 16.1847 | AO115: 10.4527 | AP115: 10.5268
A116: 43840 | B116: 40.5929 | D116: 78.4922 | F116: 10.7306 | J116: 47.66 | K116: 19.8781 | P116: 37.7872 | Q116: 27.1424 | S116: 88.7322 | AA116: 21.7875 | AI116: 14.4676 | AK116: 27.6972 | AL116: 16.8057 | AO116: 11.2996 | AP116: 10.4661
A117: 44213 | B117: 40.4808 | D117: 78.2144 | F117: 10.7318 | I117: 11.9329 | J117: 47.56 | K117: 19.7271 | P117: 37.7643 | Q117: 27.0864 | S117: 88.657 | AA117: 21.7518 | AI117: 14.4584 | AK117: 27.5959 | AL117: 16.6641 | AO117: 11.599 | AP117: 10.6061
A118: 44220 | B118: 40.3643 | D118: 78.0911 | F118: 10.7334 | I118: 12.509 | J118: 47.273 | K118: 19.4921 | P118: 37.1173 | Q118: 26.6684 | S118: 87.1351 | AA118: 22.5312 | AI118: 14.6292 | AK118: 27.6459 | AL118: 16.5313 | AO118: 12.2975 | AP118: 10.6139
A119: 44226 | B119: 39.5235 | D119: 76.4662 | F119: 10.7346 | I119: 11.9584 | J119: 46.1635 | K119: 19.0199 | P119: 36.3369 | Q119: 26.2189 | S119: 85.2732 | AA119: 22.2088 | AI119: 14.616 | AK119: 27.4219 | AL119: 16.1495 | AO119: 11.8276 | AP119: 10.3164
A120: 44233 | B120: 40.3446 | D120: 78.084 | F120: 10.7368 | I120: 12.1772 | J120: 47.2701 | K120: 19.4732 | P120: 37.3017 | Q120: 26.7246 | S120: 87.5451 | AA120: 22.7953 | AI120: 15.2136 | AK120: 27.9342 | AL120: 16.6756 | AO120: 12.5114 | AP120: 10.7781
A121: 44240 | B121: 40.7629 | D121: 78.916 | F121: 10.7376 | I121: 12.5603 | J121: 48.4104 | K121: 19.9679 | P121: 38.2553 | Q121: 27.1865 | S121: 89.784 | AA121: 22.9445 | AI121: 15.3474 | AK121: 28.1549 | AL121: 17.1163 | AO121: 13.1477 | AP121: 11.4533
A122: 44247 | B122: 40.1314 | D122: 77.7278 | F122: 10.7372 | I122: 12.5577 | J122: 48.439 | K122: 19.8335 | P122: 38.0002 | Q122: 27.0144 | S122: 89.1573 | AA122: 22.9317 | AI122: 15.421 | AK122: 28.0379 | AL122: 16.8963 | AO122: 12.9489 | AP122: 11.4327
A123: 44254 | B123: 40.245 | D123: 77.9276 | F123: 10.7368 | I123: 12.0809 | J123: 48.7584 | K123: 19.8961 | P123: 38.0548 | Q123: 27.0744 | S123: 89.2403 | AA123: 22.3882 | AI123: 15.664 | AK123: 28.0545 | AL123: 16.9213 | AO123: 11.8528 | AP123: 10.8779
A124: 44261 | B124: 41.5048 | D124: 80.2219 | F124: 10.7372 | I124: 11.8602 | J124: 50.7457 | K124: 20.5953 | P124: 39.1769 | Q124: 27.7189 | S124: 91.87 | AA124: 20.689 | AI124: 16.2041 | AK124: 28.4576 | AL124: 17.0506 | AO124: 11.223 | AP124: 10.1847
A125: 44268 | B125: 42.1196 | D125: 81.3608 | F125: 10.7397 | I125: 11.8681 | J125: 51.2319 | K125: 20.9817 | P125: 39.7824 | Q125: 28.0571 | S125: 93.3109 | AA125: 21.6213 | AI125: 16.5401 | AK125: 28.6622 | AL125: 17.3367 | AO125: 11.0909 | AP125: 10.3213
A126: 44275 | B126: 41.8458 | D126: 80.8907 | F126: 10.7432 | I126: 11.1701 | J126: 51.1029 | K126: 20.7823 | P126: 39.5601 | Q126: 27.9115 | S126: 92.7987 | AA126: 21.2379 | AI126: 16.769 | AK126: 28.6598 | AL126: 17.1784 | AO126: 11.0757 | AP126: 10.2231
A127: 44282 | B127: 42.0652 | D127: 81.312 | F127: 10.7466 | I127: 10.6879 | J127: 51.3747 | K127: 20.8796 | P127: 39.8481 | Q127: 28.0701 | S127: 93.4394 | AA127: 21.229 | AI127: 16.9449 | AK127: 28.7361 | AL127: 17.2244 | AO127: 10.3501 | AP127: 9.7191
A128: 44289 | B128: 42.4097 | D128: 81.9616 | F128: 10.7487 | I128: 11.0141 | J128: 51.866 | K128: 21.0151 | P128: 40.2521 | Q128: 28.2865 | S128: 94.346 | AA128: 22.1335 | AI128: 17.2971 | AK128: 28.8102 | AL128: 17.2933 | AO128: 10.9833 | AP128: 10.4244
A129: 44296 | B129: 41.5 | D129: 80.24 | F129: 10.7504 | I129: 11.1049 | J129: 51.0637 | K129: 20.6332 | P129: 39.3458 | Q129: 27.7615 | S129: 92.2517 | AA129: 22.8567 | AI129: 16.8514 | AK129: 28.6073 | AL129: 16.9 | AO129: 10.9307 | AP129: 10.6643
A130: 44303 | B130: 41.09 | D130: 79.47 | I130: 10.8623 | J130: 51.05 | K130: 20.4675 | P130: 38.7406 | Q130: 27.4224 | S130: 90.8446 | AA130: 22.9753 | AI130: 16.772 | AK130: 28.5619 | AL130: 16.6972 | AO130: 10.6198 | AP130: 10.6402
...

Sheet Tracking
A1: Date | B1: Fund | C1: Buy/Sell | D1: Amount (THB) | E1: Buffer/RMF | F1: Unit cost | G1: =SUBTOTAL(9,D:D) -> 952009.6 | H1: =3350*K1 -> 40200 | I1: =G1/H1 -> 23.681831 | J1: Month | K1: 12 | M1: KFGTECHRMF | N1: =K1*Fund!L2 -> 40200 | O1: KFCHINARMF | P1: =K1*Fund!N2 -> 40200 | Q1: K-USXNDQ-A(D) | R1: =K1*Fund!AA2 -> 60000 | S1: KCHANGERMF | T1: =K1*Fund!AD2 -> 40200 | U1: KVIETNAMRMF | V1: =K1*Fund!AG2 -> 60300 | W1: KBLRMF | X1: =Tracking!K1*Fund!AK2 -> 60300 | Y1: KSRMF | Z1: =K1*Fund!AS2 -> 1200 | AA1: SCBRMS&P500 | AB1: =K1*Fund!BB2 -> 40200 | AC1: TEURMF-A | AD1: =K1*Fund!BD2 -> 40200 | AE1: KFEURORMF | AF1: =K1*Fund!O2 -> 0 | AG1: KFGBRANRMF | AI1: Perf | AJ1: Overall Perf | AK1: Share
A2: 44964 | B2: SCBRMS&P500 | C2: Buy | D2: 2500 | E2: RMF | F2: 13.9235 | AA2: =(D2+D6+D11+D19+D27+D32+D39+D43+D48+D52+D57+D62+D72+D79+D87+D96)/((D2/F2)+(D6/F6)+(D11/F11)+(D19/F19)+(D27/F27)+(D32/F32)+(D39/F39)+(D43/F43)+(D48/F48)+(D52/F52)+(D57/F57)+(D62/F62)+(D72/F72)+(D79/F79)+(D87/F87)+(D96/F96)) -> 15.440833 | AI2: =(AA6-AA2)/AA2 -> 0.21710399 | AK2: =(D2+D6+D11+D19+D27+D32+D39+D43+D48+D52+D57+D62+D72+D79+D87+D96)/SUM(D:D) -> 0.0067012996
A3: 44964 | B3: KCHANGERMF | C3: Buy | D3: 2500 | E3: RMF | F3: 10.0452 | S3: =(D3+D23+D30+D36+D46+D59+D66+D78+D83+D91)/((D3/F3)+(D23/F23)+(D30/F30)+(D36/F36)+(D46/F46)+(D59/F59)+(D66/F66)+(D78/F78)+(D83/F83)+(D91/F91)) -> 9.4825284 | AI3: =(S23-S3)/S3 -> 0.047642527 | AK3: =(D3+D23+D30+D36+D46+D59+D66+D78+D83+D91)/SUM(D:D) -> 0.0057439711
A4: 44974 | B4: TEURMF-A | C4: Buy | D4: 1000 | E4: RMF | F4: 14.1323 | AC4: =(D4+D13+D20+D49+D63+D73+D88+D98)/((D4/F4)+(D13/F13)+(D20/F20)+(D49/F49)+(D63/F63)+(D73/F73)+(D88/F88)+(D98/F98)) -> 15.060891 | AI4: =(AC13-AC4)/AC4 -> 0.039745903 | AK4: =(D4+D13+D20+D49+D63+D73+D88+D98)/SUM(D:D) -> 0.0041028365
A5: 45012 | B5: K-USXNDQ-A(D) | C5: Buy | D5: 1500 | E5: Buffer | F5: 18.2345 | Q5: =(D5+D7+D12+D14+D15+D16+D17+D22+D25+D29+D35+D42+D45+D51+D55+D70+D77+D82+D92)/((D5/F5)+(D7/F7)+(D12/F12)+(D14/F14)+(D15/F15)+(D16/F16)+(D17/F17)+(D22/F22)+(D25/F25)+(D29/F29)+(D35/F35)+(D42/F42)+(D45/F45)+(D51/F51)+(D55/F55)+(D70/F70)+(D77/F77)+(D82/F82)+(D92/F92)) -> 22.579069 | AI5: =(Q7-Q5)/Q5 -> 0.14004698 | AK5: =(D5+D7+D12+D14+D15+D16+D17+D22+D25+D29+D35+D42+D45++D51+D55+D70+D77+D82+D92)/SUM(D:D) -> 0.0065645384
A6: 45019 | B6: SCBRMS&P500 | C6: Buy | D6: 2000 | E6: RMF | F6: 13.742 | AA6: =Fund!BB316 -> 18.7931
A7: 45019 | B7: K-USXNDQ-A(D) | C7: Buy | D7: 1000 | E7: Buffer | F7: 18.8878 | Q7: =Fund!AA316 -> 25.7412
A8: 45019 | B8: KVIETNAMRMF | C8: Buy | D8: 1000 | E8: RMF | F8: 8.2854 | U8: =(D8+D10+D18+D26+D31+D37+D40+D47+D56+D60+D64+D71+D84+D93)/((D8/F8)+(D10/F10)+(D18/F18)+(D26/F26)+(D31/F31)+(D37/F37)+(D40/F40)+(D47/F47)+(D56/F56)+(D60/F60)+(D64/F64)+(D71/F71)+(D84/F84)+(D93/F93)) -> 8.7473374 | AI8: =(U10-U8)/U8 -> 0.058607845 | AK8: =(D8+D10+D18+D26+D31+D37+D40+D47+D56+D60+D64+D71+D84+D93)/SUM(D:D) -> 0.0064277771
A9: 45019 | B9: KSRMF | C9: Buy | D9: 1000 | E9: RMF | F9: 23.7089 | Y9: =(D9+D38+D61+D65+D69+D86+D97)/((D9/F9)+(D38/F38)+(D61/F61)+(D65/F65)+(D69/F69)+(D86/F86)+(D97/F97)) -> 21.221611 | AI9: =(Y38-Y9)/Y9 -> -0.0048022169 | AK9: =(D9+D38+D61+D65+D69+D86+D97)/SUM(D:D) -> 0.003829314
A10: 45026 | B10: KVIETNAMRMF | C10: Buy | D10: 1000 | E10: RMF | F10: 8.2181 | U10: =Fund!AG316 -> 9.26
A11: 45026 | B11: SCBRMS&P500 | C11: Buy | D11: 1500 | E11: RMF | F11: 13.6899
A12: 45026 | B12: K-USXNDQ-A(D) | C12: Buy | D12: 1000 | E12: Buffer | F12: 18.7329
A13: 45034 | B13: TEURMF-A | C13: Buy | D13: 1000 | E13: RMF | F13: 14.3671 | AC13: =Fund!BD316 -> 15.6595
A14: 45048 | B14: K-USXNDQ-A(D) | C14: Buy | D14: 1000 | E14: Buffer | F14: 18.7796
A15: 45055 | B15: K-USXNDQ-A(D) | C15: Buy | D15: 1000 | E15: Buffer | F15: 18.8609
A16: 45062 | B16: K-USXNDQ-A(D) | C16: Buy | D16: 1000 | E16: Buffer | F16: 19.1733
A17: 45069 | B17: K-USXNDQ-A(D) | C17: Buy | D17: 1000 | E17: Buffer | F17: 19.579
A18: 45069 | B18: KVIETNAMRMF | C18: Buy | D18: 1000 | E18: RMF | F18: 8.1638
A19: 45069 | B19: SCBRMS&P500 | C19: Buy | D19: 1000 | E19: RMF | F19: 13.7765
A20: 45069 | B20: TEURMF-A | C20: Buy | D20: 1000 | E20: RMF | F20: 14.416
A21: 45076 | B21: KFGTECHRMF | C21: Buy | D21: 1000 | E21: RMF | F21: 11.0279 | M21: =(D21+D24+D28+D33+D41+D44+D53+D58+D68+D75+D80+D95+D100)/((D21/F21)+(D24/F24)+(D28/F28)+(D33/F33)+(D41/F41)+(D44/F44)+(D53/F53)+(D58/F58)+(D68/F68)+(D75/F75)+(D80/F80)+(D95/F95)+(D100/F100)) -> 13.574325 | AI21: =(M24-M21)/M21 -> 0.10486522 | AK21: =(D21+D24+D28+D33+D41+D44+D53+D58+D68+D75+D80+D95+D100)/SUM(D:D) -> 0.029592077
A22: 45076 | B22: K-USXNDQ-A(D) | C22: Buy | D22: 1000 | E22: Buffer | F22: 20.538
A23: 45076 | B23: KCHANGERMF | C23: Buy | D23: 1000 | E23: RMF | F23: 9.601 | S23: =Fund!AD316 -> 9.9343
A24: 45084 | B24: KFGTECHRMF | C24: Buy | D24: 1000 | E24: RMF | F24: 11.2298 | M24: =Fund!L316 -> 14.9978
A25: 45084 | B25: K-USXNDQ-A(D) | C25: Buy | D25: 1000 | E25: Buffer | F25: 20.156
A26: 45084 | B26: KVIETNAMRMF | C26: Buy | D26: 1000 | E26: RMF | F26: 8.4854
A27: 45084 | B27: SCBRMS&P500 | C27: Buy | D27: 1000 | E27: RMF | F27: 14.1725
A28: 45092 | B28: KFGTECHRMF | C28: Buy | D28: 1000 | E28: RMF | F28: 11.4134
A29: 45091 | B29: K-USXNDQ-A(D) | C29: Buy | D29: 1000 | E29: Buffer | F29: 21.0998
A30: 45092 | B30: KCHANGERMF | C30: Buy | D30: 1000 | E30: RMF | F30: 9.9545
A31: 45092 | B31: KVIETNAMRMF | C31: Buy | D31: 1000 | E31: RMF | F31: 8.5083
A32: 45091 | B32: SCBRMS&P500 | C32: Buy | D32: 1000 | E32: RMF | F32: 14.4917
A33: 45099 | B33: KFGTECHRMF | C33: Buy | D33: 1000 | E33: RMF | F33: 11.1652
A34: 45098 | B34: KFCHINARMF | C34: Buy | D34: 1000 | E34: RMF | F34: 10.1209 | O34: =(D34+D67+D76+D81+D94)/((D34/F34)+(D67/F67)+(D76/F76)+(D81/F81)+(D94/F94)) -> 9.1937524 | AI34: =(O67-O34)/O34 -> 0.010327409 | AK34: =(D34+D67+D76+D81+D94)/SUM(D:D) -> 0.0047866426
A35: 45098 | B35: K-USXNDQ-A(D) | C35: Buy | D35: 1000 | E35: Buffer | F35: 20.9058
A36: 45099 | B36: KCHANGERMF | C36: Buy | D36: 1000 | E36: RMF | F36: 9.7249
A37: 45099 | B37: KVIETNAMRMF | C37: Buy | D37: 1000 | E37: RMF | F37: 8.623
A38: 45098 | B38: KSRMF | C38: Buy | D38: 1000 | E38: RMF | F38: 22.5314 | Y38: =Fund!AS316 -> 21.1197
A39: 45098 | B39: SCBRMS&P500 | C39: Buy | D39: 1000 | E39: RMF | F39: 14.4687
A40: 45105 | B40: KVIETNAMRMF | C40: Buy | D40: 1000 | E40: RMF | F40: 8.8924
A41: 45105 | B41: KFGTECHRMF | C41: Buy | D41: 1000 | E41: RMF | F41: 11.2353
A42: 45105 | B42: K-USXNDQ-A(D) | C42: Buy | D42: 1000 | E42: Buffer | F42: 21.0764
A43: 45105 | B43: SCBRMS&P500 | C43: Buy | D43: 1000 | E43: RMF | F43: 14.5147
A44: 45113 | B44: KFGTECHRMF | C44: Buy | D44: 1000 | E44: RMF | F44: 11.0834
A45: 45112 | B45: K-USXNDQ-A(D) | C45: Buy | D45: 1000 | E45: Buffer | F45: 21.3668
A46: 45113 | B46: KCHANGERMF | C46: Buy | D46: 1000 | E46: RMF | F46: 9.7091
A47: 45114 | B47: KVIETNAMRMF | C47: Buy | D47: 1000 | E47: RMF | F47: 8.7284
A48: 45112 | B48: SCBRMS&P500 | C48: Buy | D48: 1000 | E48: RMF | F48: 14.7236
A49: 45114 | B49: TEURMF-A | C49: Buy | D49: 1000 | E49: RMF | F49: 13.9046
A50: 45114 | B50: KFEURORMF | C50: Buy | D50: 1000 | E50: RMF | F50: 16.1695 | AE50: =(D50+D54)/((D50/F50)+(D54/F54)) -> 16.503073 | AI50: =(AE54-AE50)/AE50 -> 0.032856092 | AK50: =(D50+D54)/SUM(D:D) -> 0.00027352243
A51: 45119 | B51: K-USXNDQ-A(D) | C51: Buy | D51: 1000 | E51: Buffer | F51: 21.4963
A52: 45119 | B52: SCBRMS&P500 | C52: Buy | D52: 1000 | E52: RMF | F52: 14.8004
A53: 45125 | B53: KFGTECHRMF | C53: Buy | D53: 1000 | E53: RMF | F53: 11.6965
A54: 45128 | B54: KFEURORMF | C54: Buy | D54: 1000 | E54: RMF | F54: 16.8507 | AE54: =Fund!O316 -> 17.0453
A55: 45125 | B55: K-USXNDQ-A(D) | C55: Buy | D55: 1000 | E55: Buffer | F55: 22.1692
A56: 45125 | B56: KVIETNAMRMF | C56: Buy | D56: 1000 | E56: RMF | F56: 8.7801
A57: 45125 | B57: SCBRMS&P500 | C57: Buy | D57: 1000 | E57: RMF | F57: 15.0387
A58: 45131 | B58: KFGTECHRMF | C58: Buy | D58: 1000 | E58: RMF | F58: 11.3219
A59: 45131 | B59: KCHANGERMF | C59: Buy | D59: 1000 | E59: RMF | F59: 9.8033
A60: 45133 | B60: KVIETNAMRMF | C60: Buy | D60: 1000 | E60: RMF | F60: 9.0952
A61: 45134 | B61: KSRMF | C61: Buy | D61: 1000 | E61: RMF | F61: 23.1139
A62: 45135 | B62: SCBRMS&P500 | C62: Buy | D62: 1000 | E62: RMF | F62: 14.9648
A63: 45131 | B63: TEURMF-A | C63: Buy | D63: 1000 | E63: RMF | F63: 14.4432
A64: 45155 | B64: KVIETNAMRMF | C64: Buy | D64: 1000 | E64: RMF | F64: 9.5521
A65: 45155 | B65: KSRMF | C65: Buy | D65: 1000 | E65: RMF | F65: 23.3033
A66: 45236 | B66: KCHANGERMF | C66: Buy | D66: 5000 | E66: RMF | F66: 8.6148
A67: 45236 | B67: KFCHINARMF | C67: Buy | D67: 5000 | E67: RMF | F67: 9.1218 | O67: =Fund!N316 -> 9.2887
A68: 45236 | B68: KFGTECHRMF | C68: Buy | D68: 2000 | E68: RMF | F68: 10.7356
A69: 45236 | B69: KSRMF | C69: Buy | D69: 1000 | E69: RMF | F69: 21.9409
A70: 45236 | B70: K-USXNDQ-A(D) | C70: Buy | D70: 2500 | E70: Buffer | F70: 20.6793
A71: 45236 | B71: KVIETNAMRMF | C71: Buy | D71: 4000 | E71: RMF | F71: 8.2396
A72: 45236 | B72: SCBRMS&P500 | C72: Buy | D72: 5000 | E72: RMF | F72: 14.2543
A73: 45236 | B73: TEURMF-A | C73: Buy | D73: 3000 | E73: RMF | F73: 13.6899
A74: 45236 | B74: KBLRMF | C74: Buy | D74: 5000 | E74: RMF | F74: 28.2404 | W74: =(D74+D85+D90)/((D74/F74)+(D85/F85)+(D90/F90)) -> 28.101501 | AI74: =(W85-W74)/W74 -> 0.013928047 | AK74: =(D74+D85+D90)/SUM(D:D) -> 0.0039660753
A75: 45251 | B75: KFGTECHRMF | C75: Buy | D75: 2000 | E75: RMF | F75: 11.6331
A76: 45251 | B76: KFCHINARMF | C76: Buy | D76: 2000 | E76: RMF | F76: 9.2577
A77: 45251 | B77: K-USXNDQ-A(D) | C77: Buy | D77: 2000 | E77: Buffer | F77: 21.7393
A78: 45251 | B78: KCHANGERMF | C78: Buy | D78: 2500 | E78: RMF | F78: 9.029
A79: 45251 | B79: SCBRMS&P500 | C79: Buy | D79: 2000 | E79: RMF | F79: 14.7879
A80: 45287 | B80: KFGTECHRMF | C80: Buy | D80: 15000 | E80: RMF | F80: 12.2736
A81: 45288 | B81: KFCHINARMF | C81: Buy | D81: 15000 | E81: RMF | F81: 9.0258
A82: 45286 | B82: K-USXNDQ-A(D) | C82: Buy | D82: 10000 | E82: Buffer | F82: 22.5602
A83: 45287 | B83: KCHANGERMF | C83: Buy | D83: 15000 | E83: RMF | F83: 9.576
A84: 45286 | B84: KVIETNAMRMF | C84: Buy | D84: 20000 | E84: RMF | F84: 8.2942
A85: 45286 | B85: KBLRMF | C85: Buy | D85: 10000 | E85: RMF | F85: 28.3896 | W85: =Fund!AK316 -> 28.4929
A86: 45286 | B86: KSRMF | C86: Buy | D86: 8000 | E86: RMF | F86: 22.0985
A87: 45286 | B87: SCBRMS&P500 | C87: Buy | D87: 15000 | E87: RMF | F87: 15.4863
A88: 45287 | B88: TEURMF-A | C88: Buy | D88: 10000 | E88: RMF | F88: 14.7344
A89: 45441 | B89: KFGBRANRMF | C89: Buy | D89: 500 | E89: RMF | F89: 16.1266 | AG89: =(D89+D101)/((D89/F89)+(D101/F101)) -> 16.608829 | AI89: =(AG101-AG89)/AG89 -> 0.041409964 | AK89: =(D89+D101)/SUM(D:D) -> 0.059545786
A90: 45489 | B90: KBLRMF | C90: Buy | D90: 14000 | E90: RMF | F90: 27.8507
A91: 45489 | B91: KCHANGERMF | C91: Buy | D91: 12000 | E91: RMF | F91: 9.6449
A92: 45488 | B92: K-USXNDQ-A(D) | C92: Buy | D92: 18000 | E92: Buffer | F92: 26.0034
A93: 45489 | B93: KVIETNAMRMF | C93: Buy | D93: 12000 | E93: RMF | F93: 9.9626
A94: 45489 | B94: KFCHINARMF | C94: Buy | D94: 12000 | E94: RMF | F94: 9.36
A95: 45488 | B95: KFGTECHRMF | C95: Buy | D95: 12000 | E95: RMF | F95: 15.4394
A96: 45488 | B96: SCBRMS&P500 | C96: Buy | D96: 12000 | E96: RMF | F96: 18.0407
A97: 45489 | B97: KSRMF | C97: Buy | D97: 15000 | E97: RMF | F97: 20.2955
A98: 45489 | B98: TEURMF-A | C98: Buy | D98: 12000 | E98: RMF | F98: 16.1463
A99: 45496 | B99: KFFLEX2RMF | C99: Switch-Out | E99: RMF | F99: 40.7707
A100: 45498 | B100: KFGTECHRMF | C100: Switch-In | D100: 177377.7 | E100: RMF | F100: 13.7794
...

Sheet Tool
C1: Budget | D1: %Allot_Act | E1: %Allot_Tgt | F1: %Allot_Today | G1: %Per
C2: =33500*12*0.3 -> 120600 | D2: =SUM(D3:D11) -> 0.071714532 | E2: =SUM(E3:E11) -> 1 | F2: =SUM(C3:C11)/C2 -> 1 | I2: =120000*6+200000*6 -> 1920000 | J2: =I2*0.3-100000 -> 476000
A3: Kbank | B3: KBLRMF | C3: =$C$2*E3 -> 14472 | D3: =Tracking!AK74 -> 0.0039660753 | E3: 0.12 | G3: =Tracking!AI74 -> 0.013928047
A4: Kbank | B4: KCHANGERMF | C4: =$C$2*E4 -> 12060 | D4: =Tracking!AK3 -> 0.0057439711 | E4: 0.1
A5: Krungsri | B5: KF-GCHINARMF | C5: =$C$2*E5 -> 12060 | D5: =Tracking!AK34 -> 0.0047866426 | E5: 0.1
A6: Krungsri | B6: KFGTECHRMF | C6: =$C$2*E6 -> 12060 | D6: =Tracking!AK21 -> 0.029592077 | E6: 0.1
A7: Finno | B7: KSRMF | C7: =$C$2*E7 -> 15678 | D7: =Tracking!AK9 -> 0.003829314 | E7: 0.13 | G7: =Tracking!AI9 -> -0.0048022169
A8: Kbank | B8: K-USXNDQ-A(D) | C8: =$C$2*E8 -> 18090 | D8: =Tracking!AK5 -> 0.0065645384 | E8: 0.15
A9: Kbank | B9: KVIETNAMRMF | C9: =$C$2*E9 -> 12060 | D9: =Tracking!AK8 -> 0.0064277771 | E9: 0.1
A10: SCB | B10: SCBRMS&P500 | C10: =$C$2*E10 -> 12060 | D10: =Tracking!AK2 -> 0.0067012996 | E10: 0.1
A11: Finno | B11: TEURMF-A | C11: =$C$2*E11 -> 12060 | D11: =Tracking!AK4 -> 0.0041028365 | E11: 0.1
C12: 230500
A13: Krungsri | B13: KFGBRANRMF | C13: =C$12*E13 -> 69150 | E13: 0.3
A14: Krungsri | B14: KFGTECHRMF | C14: =C$12*E14 -> 34575 | E14: 0.15
A15: Krungsri | B15: KFCHINARMF | C15: =C$12*E15 -> 23050 | E15: 0.1
A16: Kbank | B16: KCHANGERMF | C16: =C$12*E16 -> 23050 | E16: 0.1
A17: Kbank | B17: KVIETNAMRMF | C17: =C$12*E17 -> 23050 | E17: 0.1
A18: SCB | B18: SCBRMS&P500 | C18: =C$12*E18 -> 34575 | E18: 0.15
A19: Kbank | B19: KBLRMF | C19: =C$12*E19 -> 23050 | E19: 0.1
A21: Kbank | B21: K-USXNDQ-A(D) | C21: 50000

Sheet Snapshot
B1: Aberdeen | C1: Krungsri | D1: BuaLuang | E1: Finnomena | F1: Kbank | G1: SCB | I1: 46193 | J1: Values | K1: 1-M diff | L1: %Cont | M1: %Gold | N1: Wk18 | O1: Wk19 | P1: wk01 | Q1: wk02 | R1: wk03 | S1: wk04 | T1: wk05 | U1: wk06 | V1: wk07 | W1: wk08 | X1: wk09 | Y1: wk10 | Z1: wk11 | AA1: wk12 | AB1: wk13 | AC1: wk14 | AD1: wk15 | AE1: wk16 | AF1: wk17 | AG1: wk18 | AH1: wk19 | AI1: wk20 | AJ1: wk21 | AK1: wk22 | AL1: wk23 | AM1: wk24 | AN1: wk25
A2: ABSC-RMF | B2: 591.2952 | I2: =Fund!D399 -> 76.3887 | J2: =I2*B2 -> 45168.272 | K2: =Fund!D503 -> 0.019738326 | L2: =J2/$J$38 -> 0.011733354 | M2: =(J9+J11+J16+J32+J33+J20)/J38 -> 0.20722429 | N2: 2733007.1 | O2: 2785909.7 | P2: 3513531.2 | Q2: 3616710.6 | R2: 3663144.8 | S2: 3710714.5 | T2: 3796291.7 | U2: 3683621.4 | V2: 3738622.6 | W2: 3759449 | X2: 3816846 | Y2: 3740690 | Z2: 3710691.6 | AA2: 3611528.5 | AB2: 3534700.1 | AC2: 3587694.2 | AD2: 3685534.3 | AE2: 3747928.3 | AF2: 3785580.9 | AG2: 3779569.7 | AH2: 3889388.5 | AI2: 3857580 | AJ2: 3863825.5 | AK2: 3902469.7 | AL2: 3938158.1 | AM2: 3789302.9 | AN2: 3849562
A3: ABGDD-RMF | B3: =1095.0987+4933.3731+5959.5147+9866.7467+4933.3728 -> 26788.106 | I3: =Fund!E399 -> 13.5728 | J3: =I3*B3 -> 363589.61 | K3: =Fund!E503 -> -0.00026516602 | L3: =J3/$J$38 -> 0.094449605
A4: ABAGS | B4: 785.0426 | I4: =Fund!C399 -> 20.0155 | J4: =I4*B4 -> 15713.02 | K4: =Fund!C503 -> 0.058617881 | L4: =J4/$J$38 -> 0.0040817684
A5: KF-GOLD | C5: 275.3748
A6: KF-GCHINARMF | C6: 11137.173 | I6: =Fund!N399 -> 12.118 | J6: =I6*C6 -> 134960.26 | K6: =Fund!N503 -> 0.031310372 | L6: =J6/$J$38 -> 0.035058602
A7: KFGBRANRMF | C7: 21708.492 | I7: =Fund!G399 -> 14.0867 | J7: =I7*C7 -> 305801.01 | K7: =Fund!G503 -> -0.030876131 | L7: =J7/$J$38 -> 0.079437871
A8: KFAFIXRMF | C8: 1694.8662 | I8: =Fund!H399 -> 14.0867 | J8: =I8*C8 -> 23875.072 | K8: =Fund!H503 -> 0.19200014 | L8: =J8/$J$38 -> 0.006202023
A9: KFGOLDRMF | C9: =6087.7086+2710.1492 -> 8797.8578 | I9: =Fund!M399 -> 24.284 | J9: =I9*C9 -> 213647.18 | K9: =Fund!M503 -> -0.082542465 | L9: =J9/$J$38 -> 0.055499088
A10: KFGTECHRMF | C10: 9887.1611 | I10: =Fund!L399 -> 25.6954 | J10: =I10*C10 -> 254054.56 | K10: =Fund!L503 -> 0.078985824 | L10: =J10/$J$38 -> 0.065995706
A11: BGOLDRMF | D11: 14613.117 | I11: =Fund!T399 -> 27.918 | J11: =I11*D11 -> 407969.01 | K11: =Fund!T503 -> -0.073845541 | L11: =J11/$J$38 -> 0.10597803 | M11: =D11*0.4 -> 5845.2469 | N11: =J11*0.3 -> 122390.7 | O11: =J11-N11 -> 285578.3
A12: B-INNOTECHRMF | D12: 18092.878 | I12: =Fund!U399 -> 34.4114 | J12: =I12*D12 -> 622601.26 | K12: =Fund!U503 -> 0.004539364 | L12: =J12/$J$38 -> 0.16173301
A13: RE | D13: 890.67 | I13: =Fund!S399 -> 80.8324 | J13: =I13*D13 -> 71994.994 | K13: =Fund!S503 -> 0.015087089 | L13: =J13/$J$38 -> 0.018702126
A14: ESGXBMDIV-SW | D14: 12106.368 | I14: =Fund!R399 -> 11.625 | J14: =I14*D14 -> 140736.53 | K14: =Fund!R503 -> 0.018869909 | L14: =J14/$J$38 -> 0.036559103
A15: MEGA10CHINA-A | E15: 800.0139 | I15: =Fund!V399 -> 11.7986 | J15: =I15*E15 -> 9439.044 | K15: =Fund!V503 -> -0.061614691 | L15: =J15/$J$38 -> 0.0024519787
A16: KT-GOLD RMF | E16: 1688.2758 | I16: =Fund!AU399 -> 21.5934 | J16: =I16*E16 -> 36455.615 | K16: =Fund!AU503 -> -0.079855459 | L16: =J16/$J$38 -> 0.0094700683
A17: TEURMF-A | E17: 1991.9136 | I17: =Fund!BD399 -> 19.9084 | J17: =I17*E17 -> 39655.813 | K17: =Fund!BD503 -> 0.024331764 | L17: =J17/$J$38 -> 0.010301383
A18: KT-BLOCKCHAIN-A | E18: 344.0433 | I18: =Fund!W399 -> 16.2881 | J18: =I18*E18 -> 5603.8117 | K18: =Fund!W503 -> 0.029576112 | L18: =J18/$J$38 -> 0.0014557011
A19: TCHRMF | E19: 10499.377 | I19: =Fund!AQ399 -> 6.7773 | J19: =I19*E19 -> 71157.425 | K19: =Fund!AQ503 -> -0.062847424 | L19: =J19/$J$38 -> 0.018484551
A20: DAOL-GOLDRMF | E20: 3281.2346 | I20: =Fund!AW399 -> 16.7415 | J20: =I20*E20 -> 54932.789 | K20: =Fund!AW503 -> -0.047923704 | L20: =J20/$J$38 -> 0.014269881
A21: ES-EGRMF | E21: 4236.6777 | I21: =Fund!AV399 -> 24.0481 | J21: =I21*E21 -> 101884.05 | K21: =Fund!AV503 -> 0.014118659 | L21: =J21/$J$38 -> 0.026466401
A22: KKP TECH RMF-H | E22: 6363.59 | I22: =Fund!AR399 -> 19.4822 | J22: =I22*E22 -> 123976.73 | K22: =Fund!AR503 -> 0.053376588 | L22: =J22/$J$38 -> 0.032205413
A23: TDSThaiESG-A | E23: =4876.7641+4897.0157 -> 9773.7798 | I23: =Fund!AT399 -> 13.4566 | J23: =I23*E23 -> 131521.85 | K23: =Fund!AT503 -> 0.03940061 | L23: =J23/$J$38 -> 0.034165406
A24: SCBRMJP | G24: 2272.9941 | I24: =Fund!AX399 -> 37.4804 | J24: =I24*G24 -> 85192.728 | K24: =Fund!AX503 -> 0.12711143 | L24: =J24/$J$38 -> 0.022130499
A25: SCBAUD | G25: 941.3625 | I25: =Fund!BC399 -> 10.9107 | J25: =I25*G25 -> 10270.924 | K25: =Fund!BC503 -> -0.0092350441 | L25: =J25/$J$38 -> 0.002668076
A26: K-VIETNAMRMF | F26: 5351.3142 | I26: =Fund!AG399 -> 9.9677 | J26: =I26*F26 -> 53340.295 | K26: =Fund!AG503 -> -0.001362548 | L26: =J26/$J$38 -> 0.013856198
A27: K-CHANGERMF | F27: 5588.8369 | I27: =Fund!AD399 -> 10.8658 | J27: =I27*F27 -> 60727.184 | K27: =Fund!AD503 -> 0.062088245 | L27: =J27/$J$38 -> 0.015775089
A28: K-CHINARMF | F28: 7505.8617 | I28: =Fund!AO399 -> 5.4936 | J28: =I28*F28 -> 41234.202 | K28: =Fund!AO503 -> -0.028300552 | L28: =J28/$J$38 -> 0.010711401
A29: K-USXNDQ-A(D) | F29: 257.6078 | I29: =Fund!AA399 -> 31.8135 | J29: =I29*F29 -> 8195.4057 | K29: =Fund!AA503 -> 0.017751915 | L29: =J29/$J$38 -> 0.002128919
A30: K-BLRMF | F30: 5626.0102 | I30: =Fund!AK399 -> 29.7152 | J30: =I30*F30 -> 167178.02 | K30: =Fund!AK503 -> 0.014084123 | L30: =J30/$J$38 -> 0.043427803
A31: K-70ThaiESGX-L | F31: 4347.2685 | I31: =Fund!AN399 -> 11.5278 | J31: =I31*F31 -> 50114.442 | K31: =Fund!AN503 -> 0.020339883 | L31: =J31/$J$38 -> 0.013018219
A32: K-GDRMF | F32: 2842.6581 | I32: =Fund!AJ399 -> 28.3801 | J32: =I32*F32 -> 80674.921 | K32: =Fund!AJ503 -> -0.061262495 | L32: =J32/$J$38 -> 0.020956909
A33: SCBGOLDHE | G33: 211.6751 | I33: =Fund!AZ399 -> 19.1011 | J33: =I33*G33 -> 4043.2273 | K33: =Fund!AZ503 -> -0.081147778 | L33: =J33/$J$38 -> 0.0010503084
A34: SCBRMS&P500 | G34: 4995.5182 | I34: =Fund!BB399 -> 22.5283 | J34: =I34*G34 -> 112540.53 | K34: =Fund!BB503 -> 0.0048305085 | L34: =J34/$J$38 -> 0.029234633
A35: SCBS&P500 | G35: 45.864 | I35: =Fund!BA399 -> 28.6104 | J35: =I35*G35 -> 1312.1874 | K35: =Fund!BA503 -> -0.063339128 | L35: =J35/$J$38 -> 0.00034086668
J38: =SUM(J2:J35) -> 3849562
